flipflopD/FFD.v
module FFD(
    input wire D,
    input wire clk,
    input wire set, 
    input wire reset,
    input wire enable,
    output wire Q,Qn 
);

reg salida = 0;

always  @(posedge clk or posedge reset or posedge set) begin
        if (reset)
            salida <= 0;
        else if (set)
            salida <= 1;
        else if (enable)
            salida <= D; 

    end

    assign Q = salida;
    assign Qn = ~salida;

endmodule

Reg4Universal/Reg.v
`include "FFD/FFD.v"

module Reg(
    input wire clk,
    input wire reset,
    input wire set,
    input wire enable,
    input wire [1:0] mode,
    input wire [3:0] P_in,
    input wire S_in,
    output wire [3:0] P_out,
    output wire S_out
);

wire [3:0] D_in;
wire [3:0] Q, Qn;

//Lógica de cada FFD
assign D_in[0] = (mode == 2'b01) ? S_in :
                 (mode == 2'b10) ? Q[1] :
                 (mode == 2'b11) ? P_in[0] : Q[0];

assign D_in[1] = (mode == 2'b01) ? Q[0] :
                 (mode == 2'b10) ? Q[2] :
                 (mode == 2'b11) ? P_in[1] : Q[1];

assign D_in[2] = (mode == 2'b01) ? Q[1] :
                 (mode == 2'b10) ? Q[3] :
                 (mode == 2'b11) ? P_in[2] : Q[2];

assign D_in[3] = (mode == 2'b01) ? Q[2] :
                 (mode == 2'b10) ? S_in :
                 (mode == 2'b11) ? P_in[3] : Q[3];

// Instanciamos cada FFD
genvar i;
generate
    for (i = 0; i < 4; i = i + 1) begin : FF_D  //FF_D almacena cada instacia de hardware
        FFD ff (   //Módulo e intancia
            .D(D_in[i]),
            .clk(clk),
            .reset(reset),
            .set(set),
            .enable(enable),
            .Q(Q[i]),
            .Qn(Qn[i])
        );
    end
endgenerate

assign P_out = Q;
assign S_out = (mode == 2'b01) ? Q[0] : // LSB
               (mode == 2'b10) ? Q[3] : // MSB
               1'bz; // Alta impedancia, no escribe nada

endmodule

Reg4Universal/Reg_tb.v
`default_nettype none
`define DUMPSTR(x) `"x.vcd`"
`timescale 100ns / 10ns

module Reg_tb();

parameter DURATION = 10;


reg clk_test=0;
always #0.5 clk_test = ~clk_test;

// Entradas
reg S_test, R_test, E_test;
reg [1:0] mode_test;
reg [3:0] P_in_test;
reg S_in_test;
reg [3:0] D_in_test;
//Salidas
wire [3:0] P_out_test;
wire S_out_test;

Reg UUT (
    .set(S_test),
    .reset(R_test),
    .enable(E_test),
    .clk(clk_test),
    .mode(mode_test),
    .P_in(P_in_test),
    .S_in(S_in_test),
    .P_out(P_out_test),
    .S_out(S_out_test)
);


initial begin
    // Inicializa las señales
    $dumpfile(`DUMPSTR(`VCD_OUTPUT));
    $dumpvars(0, Reg_tb);

    clk_test = 0; R_test = 0; S_test = 0; E_test = 0;
    mode_test = 2'b00;
    P_in_test = 4'b0000;
    S_in_test = 0;

    // Reset asíncrono
    #5 R_test = 1;
    #10 R_test = 0;

    // Set asíncrono
    #5 S_test = 1;
    #10 S_test = 0;

    // Cargar datos en paralelo (P_in)
    #5 
    E_test = 1;
    mode_test = 2'b11; // Modo carga paralela
    P_in_test = 4'b1010;
    #10;

    // Mantener valores
    mode_test = 2'b00;
    #10;

    // Desplazamiento a la derecha
    mode_test = 2'b01;
    S_in_test = 1; // Bit que entra por la izquierda
    #10;
    S_in_test = 0;
    #10;

    // Desplazamiento a la izquierda
    mode_test = 2'b10;
    S_in_test = 1; // Bit que entra por la derecha
    #10;
    S_in_test = 0;
    #10;

    // Deshabilitar el registro
    E_test = 0;
    P_in_test = 4'b1111;
    mode_test = 2'b11;
    #10;  // No debería cargar nada

    // Finalizar simulación
    #20;
    $finish;
    end
endmodule

Reg4Universal/Reg_tb.vcd
$date
	Mon May 26 18:58:57 2025
$end
$version
	Icarus Verilog
$end
$timescale
	1ps
$end
$scope module Reg_tb $end
$var wire 1 ! S_out_test $end
$var wire 4 " P_out_test [3:0] $end
$var parameter 32 # DURATION $end
$var reg 1 $ E_test $end
$var reg 4 % P_in_test [3:0] $end
$var reg 1 & R_test $end
$var reg 1 ' S_in_test $end
$var reg 1 ( S_test $end
$var reg 1 ) clk_test $end
$var reg 2 * mode_test [1:0] $end
$scope module UUT $end
$var wire 4 + P_in [3:0] $end
$var wire 4 , P_out [3:0] $end
$var wire 1 ' S_in $end
$var wire 1 ) clk $end
$var wire 1 $ enable $end
$var wire 2 - mode [1:0] $end
$var wire 1 & reset $end
$var wire 1 ( set $end
$var wire 1 ! S_out $end
$var wire 4 . Qn [3:0] $end
$var wire 4 / Q [3:0] $end
$var wire 4 0 D_in [3:0] $end
$scope begin FF_D[0] $end
$var parameter 2 1 i $end
$scope module ff $end
$var wire 1 2 D $end
$var wire 1 3 Q $end
$var wire 1 4 Qn $end
$var wire 1 ) clk $end
$var wire 1 $ enable $end
$var wire 1 & reset $end
$var wire 1 ( set $end
$var reg 1 5 salida $end
$upscope $end
$upscope $end
$scope begin FF_D[1] $end
$var parameter 2 6 i $end
$scope module ff $end
$var wire 1 7 D $end
$var wire 1 8 Q $end
$var wire 1 9 Qn $end
$var wire 1 ) clk $end
$var wire 1 $ enable $end
$var wire 1 & reset $end
$var wire 1 ( set $end
$var reg 1 : salida $end
$upscope $end
$upscope $end
$scope begin FF_D[2] $end
$var parameter 3 ; i $end
$scope module ff $end
$var wire 1 < D $end
$var wire 1 = Q $end
$var wire 1 > Qn $end
$var wire 1 ) clk $end
$var wire 1 $ enable $end
$var wire 1 & reset $end
$var wire 1 ( set $end
$var reg 1 ? salida $end
$upscope $end
$upscope $end
$scope begin FF_D[3] $end
$var parameter 3 @ i $end
$scope module ff $end
$var wire 1 A D $end
$var wire 1 B Q $end
$var wire 1 C Qn $end
$var wire 1 ) clk $end
$var wire 1 $ enable $end
$var wire 1 & reset $end
$var wire 1 ( set $end
$var reg 1 D salida $end
$upscope $end
$upscope $end
$upscope $end
$upscope $end
$enddefinitions $end
$comment Show the parameter values. $end
$dumpall
b11 @
b10 ;
b1 6
b0 1
b1010 #
$end
#0
$dumpvars
0D
1C
0B
0A
0?
1>
0=
0<
0:
19
08
07
05
14
03
02
b0 0
b0 /
b1111 .
b0 -
b0 ,
b0 +
b0 *
0)
0(
0'
0&
b0 %
0$
b0 "
z!
$end
#50000
1)
#100000
0)
#150000
1)
#200000
0)
#250000
1)
#300000
0)
#350000
1)
#400000
0)
#450000
1)
#500000
0)
1&
#550000
1)
#600000
0)
#650000
1)
#700000
0)
#750000
1)
#800000
0)
#850000
1)
#900000
0)
#950000
1)
#1000000
0)
#1050000
1)
#1100000
0)
#1150000
1)
#1200000
0)
#1250000
1)
#1300000
0)
#1350000
1)
#1400000
0)
#1450000
1)
#1500000
0)
0&
#1550000
1)
#1600000
0)
#1650000
1)
#1700000
0)
#1750000
1)
#1800000
0)
#1850000
1)
#1900000
0)
#1950000
1)
#2000000
1A
1<
17
12
b1111 0
0C
0>
09
b0 .
04
1B
1D
1=
1?
18
1:
b1111 "
b1111 ,
b1111 /
13
15
0)
1(
#2050000
1)
#2100000
0)
#2150000
1)
#2200000
0)
#2250000
1)
#2300000
0)
#2350000
1)
#2400000
0)
#2450000
1)
#2500000
0)
#2550000
1)
#2600000
0)
#2650000
1)
#2700000
0)
#2750000
1)
#2800000
0)
#2850000
1)
#2900000
0)
#2950000
1)
#3000000
0)
0(
#3050000
1)
#3100000
0)
#3150000
1)
#3200000
0)
#3250000
1)
#3300000
0)
#3350000
1)
#3400000
0)
#3450000
1)
#3500000
02
17
0<
1A
b1010 0
0)
b1010 %
b1010 +
b11 *
b11 -
1$
#3550000
1>
b101 .
14
0=
0?
b1010 "
b1010 ,
b1010 /
03
05
1)
#3600000
0)
#3650000
1)
#3700000
0)
#3750000
1)
#3800000
0)
#3850000
1)
#3900000
0)
#3950000
1)
#4000000
0)
#4050000
1)
#4100000
0)
#4150000
1)
#4200000
0)
#4250000
1)
#4300000
0)
#4350000
1)
#4400000
0)
#4450000
1)
#4500000
0)
b0 *
b0 -
#4550000
1)
#4600000
0)
#4650000
1)
#4700000
0)
#4750000
1)
#4800000
0)
#4850000
1)
#4900000
0)
#4950000
1)
#5000000
0)
#5050000
1)
#5100000
0)
#5150000
1)
#5200000
0)
#5250000
1)
#5300000
0)
#5350000
1)
#5400000
0)
#5450000
1)
#5500000
12
07
1<
0A
b101 0
0!
0)
1'
b1 *
b1 -
#5550000
1A
0<
17
b1011 0
1!
1C
0>
19
b1010 .
04
0B
0D
1=
1?
08
0:
b101 "
b101 ,
b101 /
13
15
1)
#5600000
0)
#5650000
1<
0A
b111 0
09
1>
b100 .
0C
18
1:
0=
0?
b1011 "
b1011 ,
b1011 /
1B
1D
1)
#5700000
0)
#5750000
1A
b1111 0
1C
b1000 .
0>
0B
0D
b111 "
b111 ,
b111 /
1=
1?
1)
#5800000
0)
#5850000
b0 .
0C
b1111 "
b1111 ,
b1111 /
1B
1D
1)
#5900000
0)
#5950000
1)
#6000000
0)
#6050000
1)
#6100000
0)
#6150000
1)
#6200000
0)
#6250000
1)
#6300000
0)
#6350000
1)
#6400000
0)
#6450000
1)
#6500000
02
b1110 0
0)
0'
#6550000
07
b1100 0
0!
b1 .
14
b1110 "
b1110 ,
b1110 /
03
05
1)
#6600000
0)
#6650000
0<
b1000 0
b11 .
19
b1100 "
b1100 ,
b1100 /
08
0:
1)
#6700000
0)
#6750000
0A
b0 0
b111 .
1>
b1000 "
b1000 ,
b1000 /
0=
0?
1)
#6800000
0)
#6850000
b1111 .
1C
b0 "
b0 ,
b0 /
0B
0D
1)
#6900000
0)
#6950000
1)
#7000000
0)
#7050000
1)
#7100000
0)
#7150000
1)
#7200000
0)
#7250000
1)
#7300000
0)
#7350000
1)
#7400000
0)
#7450000
1)
#7500000
1A
b1000 0
0)
1'
b10 *
b10 -
#7550000
1<
b1100 0
1!
b111 .
0C
b1000 "
b1000 ,
b1000 /
1B
1D
1)
#7600000
0)
#7650000
17
b1110 0
b11 .
0>
b1100 "
b1100 ,
b1100 /
1=
1?
1)
#7700000
0)
#7750000
12
b1111 0
b1 .
09
b1110 "
b1110 ,
b1110 /
18
1:
1)
#7800000
0)
#7850000
b0 .
04
b1111 "
b1111 ,
b1111 /
13
15
1)
#7900000
0)
#7950000
1)
#8000000
0)
#8050000
1)
#8100000
0)
#8150000
1)
#8200000
0)
#8250000
1)
#8300000
0)
#8350000
1)
#8400000
0)
#8450000
1)
#8500000
0A
b111 0
0)
0'
#8550000
0<
b11 0
0!
b1000 .
1C
b111 "
b111 ,
b111 /
0B
0D
1)
#8600000
0)
#8650000
07
b1 0
b1100 .
1>
b11 "
b11 ,
b11 /
0=
0?
1)
#8700000
0)
#8750000
02
b0 0
b1110 .
19
b1 "
b1 ,
b1 /
08
0:
1)
#8800000
0)
#8850000
b1111 .
14
b0 "
b0 ,
b0 /
03
05
1)
#8900000
0)
#8950000
1)
#9000000
0)
#9050000
1)
#9100000
0)
#9150000
1)
#9200000
0)
#9250000
1)
#9300000
0)
#9350000
1)
#9400000
0)
#9450000
1)
#9500000
12
17
1<
1A
b1111 0
z!
0)
b11 *
b11 -
b1111 %
b1111 +
0$
