flipflopD/FFD.v
module FFD(
    input wire D,
    input wire clk,
    input wire set, 
    input wire reset,
    input wire enable,
    output wire Q,Qn 
);

reg salida = 0;

always  @(posedge clk or posedge reset or posedge set) begin
        if (reset)
            salida <= 0;
        else if (set)
            salida <= 1;
        else if (enable)
            salida <= D; 

    end

    assign Q = salida;
    assign Qn = ~salida;

endmodule

flipflopD/FFD_tb.v
`default_nettype none
`define DUMPSTR(x) `"x.vcd`"
`timescale 100ns / 10ns

module FFD_tb();

parameter DURATION = 10;


reg clk_test=0;
always #0.5 clk_test = ~clk_test;

// Entradas
reg S_test, R_test, E_test, D_test;
//Salidas
wire Q_test, Qn_test;

FFD UUT (
    .D(D_test),
    .set(S_test),
    .reset(R_test),
    .enable(E_test),
    .clk(clk_test),
    .Q(Q_test),
    .Qn(Qn_test)
);


initial begin
    // Inicializa las señales
    $dumpfile(`DUMPSTR(`VCD_OUTPUT));
    $dumpvars(0, FFD_tb);

    D_test = 0; S_test = 0; R_test = 0; E_test = 0;
    #10;

    // Test asíncrono
    R_test = 1;
    #5;
    R_test = 0;
    #10;

    S_test = 1;
    #5;
    S_test = 0;
    #10;

    //Test síncrono
    // Carga Enable
    D_test = 1;
    E_test = 1;
    #10;  // flanco de subida del clk

    // Deshabilitar y cambiar D (debería mantener Q)
    E_test = 0;
    D_test = 0;
    #10;

    // Habilitar y cargar 0
    E_test = 1;


    #20 $finish;

end

endmodule

flipflopD/FFD_tb.vcd
$date
	Mon May 26 17:56:08 2025
$end
$version
	Icarus Verilog
$end
$timescale
	1ps
$end
$scope module FFD_tb $end
$var wire 1 ! Qn_test $end
$var wire 1 " Q_test $end
$var parameter 32 # DURATION $end
$var reg 1 $ D_test $end
$var reg 1 % E_test $end
$var reg 1 & R_test $end
$var reg 1 ' S_test $end
$var reg 1 ( clk_test $end
$scope module UUT $end
$var wire 1 $ D $end
$var wire 1 " Q $end
$var wire 1 ! Qn $end
$var wire 1 ( clk $end
$var wire 1 % enable $end
$var wire 1 & reset $end
$var wire 1 ' set $end
$var reg 1 ) salida $end
$upscope $end
$upscope $end
$enddefinitions $end
$comment Show the parameter values. $end
$dumpall
b1010 #
$end
#0
$dumpvars
0)
0(
0'
0&
0%
0$
0"
1!
$end
#50000
1(
#100000
0(
#150000
1(
#200000
0(
#250000
1(
#300000
0(
#350000
1(
#400000
0(
#450000
1(
#500000
0(
#550000
1(
#600000
0(
#650000
1(
#700000
0(
#750000
1(
#800000
0(
#850000
1(
#900000
0(
#950000
1(
#1000000
0(
1&
#1050000
1(
#1100000
0(
#1150000
1(
#1200000
0(
#1250000
1(
#1300000
0(
#1350000
1(
#1400000
0(
#1450000
1(
#1500000
0(
0&
#1550000
1(
#1600000
0(
#1650000
1(
#1700000
0(
#1750000
1(
#1800000
0(
#1850000
1(
#1900000
0(
#1950000
1(
#2000000
0(
#2050000
1(
#2100000
0(
#2150000
1(
#2200000
0(
#2250000
1(
#2300000
0(
#2350000
1(
#2400000
0(
#2450000
1(
#2500000
0!
1"
1)
0(
1'
#2550000
1(
#2600000
0(
#2650000
1(
#2700000
0(
#2750000
1(
#2800000
0(
#2850000
1(
#2900000
0(
#2950000
1(
#3000000
0(
0'
#3050000
1(
#3100000
0(
#3150000
1(
#3200000
0(
#3250000
1(
#3300000
0(
#3350000
1(
#3400000
0(
#3450000
1(
#3500000
0(
#3550000
1(
#3600000
0(
#3650000
1(
#3700000
0(
#3750000
1(
#3800000
0(
#3850000
1(
#3900000
0(
#3950000
1(
#4000000
0(
1%
1$
#4050000
1(
#4100000
0(
#4150000
1(
#4200000
0(
#4250000
1(
#4300000
0(
#4350000
1(
#4400000
0(
#4450000
1(
#4500000
0(
#4550000
1(
#4600000
0(
#4650000
1(
#4700000
0(
#4750000
1(
#4800000
0(
#4850000
1(
#4900000
0(
#4950000
1(
#5000000
0(
0$
0%
#5050000
1(
#5100000
0(
#5150000
1(
#5200000
0(
#5250000
1(
#5300000
0(
#5350000
1(
#5400000
0(
#5450000
1(
#5500000
0(
#5550000
1(
#5600000
0(
#5650000
1(
#5700000
0(
#5750000
1(
#5800000
0(
#5850000
1(
#5900000
0(
#5950000
1(
#6000000
0(
1%
#6050000
1!
0"
0)
1(
