And/Eje_01.v
module Eje_01(
    input wire A,B,
    output wire X
);

assign X = A&B;

endmodule

And/Eje_01_tb.v
`default_nettype none
`define DUMPSTR(x) `"x.vcd`"
`timescale 100ns / 10ns

module Eje_01_tb();

parameter DURATION = 10;


reg clk=0;
always #0.5 clk = ~clk;

// Entradas
reg A_test, B_test;
//Salidas
wire X_test;

Eje_01 UUT (
    .A(A_test),
    .B(B_test),
    .X(X_test)
);

integer  i;
 

initial begin
    // Inicializa las señales
    $dumpfile(`DUMPSTR(`VCD_OUTPUT));
    $dumpvars(0, Eje_01_tb);

    for (i=0;i<4;i=i+1)
        begin
            A_test = i[1];
            B_test = i[0];
            #1;
        end
    //$display ("Current loop # %0d",i);
    A_test = 1'b0;
    B_test = 1'b0;
    #1;
    A_test = 1'b1;
    B_test = 1'b0;
    #1;
    A_test = 1'b1;
    B_test = 1'b1;
    #1;
    A_test = 1'b1;
    B_test = 1'b0;
    #1;
    A_test = 1'b0;
    B_test = 1'b0;
    #1;

    
    
        // Finaliza la simulación
        // $display("Simulación completada.");
    #(DURATION) $display("End of simulation");
    $finish;
    end
    
endmodule

And/Eje_01_tb.vcd
$date
	Tue Sep 09 10:21:02 2025
$end
$version
	Icarus Verilog
$end
$timescale
	1ps
$end
$scope module Eje_01_tb $end
$var wire 1 ! X_test $end
$var parameter 32 " DURATION $end
$var reg 1 # A_test $end
$var reg 1 $ B_test $end
$var reg 1 % clk $end
$var integer 32 & i [31:0] $end
$scope module UUT $end
$var wire 1 # A $end
$var wire 1 $ B $end
$var wire 1 ! X $end
$upscope $end
$upscope $end
$enddefinitions $end
$comment Show the parameter values. $end
$dumpall
b1010 "
$end
#0
$dumpvars
b0 &
0%
0$
0#
0!
$end
#50000
1%
#100000
0%
1$
b1 &
#150000
1%
#200000
0%
0$
1#
b10 &
#250000
1%
#300000
1!
0%
1$
b11 &
#350000
1%
#400000
0!
0%
0$
0#
b100 &
#450000
1%
#500000
0%
1#
#550000
1%
#600000
1!
0%
1$
#650000
1%
#700000
0!
0%
0$
#750000
1%
#800000
0%
0#
