BCD_Exc_3/BCD_Exc_3.v
module BCD_Exc_3(
    //Entradas
    input [3:0] BTN,
    //Salidas
    output [3:0] LED
);

assign LED = BTN + 3;

/*
reg [3:0] Aiken;

always @(*) begin
    if (BTN<=9)
        Aiken = BTN + 3;
    else 
        Aiken = 0;
end
assign LED = Aiken;
*/

endmodule

BCD_Exc_3/BCD_Exc_3_tb.v
`default_nettype none
`define DUMPSTR(x) `"x.vcd`"
`timescale 100ns / 10ns

module BCD_Exc_3_tb();

parameter DURATION = 10;


reg clk=0;
always #0.5 clk = ~clk;

// Entradas
reg [3:0] test_BTN;
//Salidas
wire [3:0] test_LED;

BCD_Exc_3 UUT (
    .BTN(test_BTN),
    .LED(test_LED)
);

integer  i;
reg [3:0] entradas;

initial begin
    // Inicializa las señales
    $dumpfile(`DUMPSTR(`VCD_OUTPUT));
    $dumpvars(0, BCD_Exc_3_tb);

    for (i=0; i<16; i=i+1)
    begin
        $display ("Current loop # %0d",i);
        
        #1
        entradas = i;
        test_BTN = entradas;
        end
    
        // Finaliza la simulación
        // $display("Simulación completada.");
        #(DURATION) $display("End of simulation");
        $finish;
    end
    
endmodule

BCD_Exc_3/BCD_Exc_3_tb.vcd
$date
	Fri Apr 04 15:50:27 2025
$end
$version
	Icarus Verilog
$end
$timescale
	1ps
$end
$scope module BCD_Exc_3_tb $end
$var wire 4 ! test_LED [3:0] $end
$var parameter 32 " DURATION $end
$var reg 1 # clk $end
$var reg 4 $ entradas [3:0] $end
$var reg 4 % test_BTN [3:0] $end
$var integer 32 & i [31:0] $end
$scope module UUT $end
$var wire 4 ' BTN [3:0] $end
$var wire 4 ( LED [3:0] $end
$upscope $end
$upscope $end
$enddefinitions $end
$comment Show the parameter values. $end
$dumpall
b1010 "
$end
#0
$dumpvars
bx (
bx '
b0 &
bx %
bx $
0#
bx !
$end
#50000
1#
#100000
0#
b1 &
b11 !
b11 (
b0 %
b0 '
b0 $
#150000
1#
#200000
0#
b10 &
b100 !
b100 (
b1 %
b1 '
b1 $
#250000
1#
#300000
0#
b11 &
b101 !
b101 (
b10 %
b10 '
b10 $
#350000
1#
#400000
0#
b100 &
b110 !
b110 (
b11 %
b11 '
b11 $
#450000
1#
#500000
0#
b101 &
b111 !
b111 (
b100 %
b100 '
b100 $
#550000
1#
#600000
0#
b110 &
b1000 !
b1000 (
b101 %
b101 '
b101 $
#650000
1#
#700000
0#
b111 &
b1001 !
b1001 (
b110 %
b110 '
b110 $
#750000
1#
#800000
0#
b1000 &
b1010 !
b1010 (
b111 %
b111 '
b111 $
#850000
1#
#900000
0#
b1001 &
b1011 !
b1011 (
b1000 %
b1000 '
b1000 $
#950000
1#
#1000000
0#
b1010 &
b1100 !
b1100 (
b1001 %
b1001 '
b1001 $
#1050000
1#
#1100000
0#
b1011 &
b1101 !
b1101 (
b1010 %
b1010 '
b1010 $
#1150000
1#
#1200000
0#
b1100 &
b1110 !
b1110 (
b1011 %
b1011 '
b1011 $
#1250000
1#
#1300000
0#
b1101 &
b1111 !
b1111 (
b1100 %
b1100 '
b1100 $
#1350000
1#
#1400000
0#
b1110 &
b0 !
b0 (
b1101 %
b1101 '
b1101 $
#1450000
1#
#1500000
0#
b1111 &
b1 !
b1 (
b1110 %
b1110 '
b1110 $
#1550000
1#
#1600000
0#
b10000 &
b10 !
b10 (
b1111 %
b1111 '
b1111 $
