Seg_7_func/seg_7_func.v
module seg_7_func(
    input wire A, B, C, D,
    output wire [6:0] seg_7
    );

    assign seg_7[0] = A|C|((B&D)|(~B&~D));
    assign seg_7[1] = ~B|(C&D)|(~C&~D);
    assign seg_7[2] = B|~C|D;
    assign seg_7[3] = A|(C&~D)|(~B&C)|(~B&~D)|((B&~C)&D);
    assign seg_7[4] = (C&~D)|(~B&~D);
    assign seg_7[5] = A|(B&~D)|(B&~C)|(~C&~D);
    assign seg_7[6] = (~B&C)|(B&~C)|(C&~D)|A;

endmodule

Seg_7_func/seg_7_func_tb.v
`default_nettype none
`define DUMPSTR(x) `"x.vcd`"
`timescale 100ns / 10ns

module seg_7_func_tb();

parameter DURATION = 10;


reg clk=0;
always #0.5 clk = ~clk;

// Entradas
reg [3:0] test_BTN;
//Salidas
wire [6:0] test_seg_7;

seg_7_func UUT (
    .A(test_BTN[3]),
    .B(test_BTN[2]),
    .C(test_BTN[1]),
    .D(test_BTN[0]),
    .seg_7(test_seg_7)
);

integer  i;
reg [3:0] entradas;

initial begin
    // Inicializa las señales
    $dumpfile(`DUMPSTR(`VCD_OUTPUT));
    $dumpvars(0, seg_7_func_tb);

    for (i=0; i<10; i=i+1)
    begin
        $display ("Current loop # %0d",i);
        
        #1
        entradas = i;
        test_BTN = entradas;
        end
    
        // Finaliza la simulación
        // $display("Simulación completada.");
        #(DURATION) $display("End of simulation");
        $finish;
    end
    
endmodule

Seg_7_func/seg_7_func_tb.vcd
$date
	Tue Apr 08 16:34:14 2025
$end
$version
	Icarus Verilog
$end
$timescale
	1ps
$end
$scope module seg_7_func_tb $end
$var wire 7 ! test_seg_7 [6:0] $end
$var parameter 32 " DURATION $end
$var reg 1 # clk $end
$var reg 4 $ entradas [3:0] $end
$var reg 4 % test_BTN [3:0] $end
$var integer 32 & i [31:0] $end
$scope module UUT $end
$var wire 1 ' A $end
$var wire 1 ( B $end
$var wire 1 ) C $end
$var wire 1 * D $end
$var wire 7 + seg_7 [6:0] $end
$upscope $end
$upscope $end
$enddefinitions $end
$comment Show the parameter values. $end
$dumpall
b1010 "
$end
#0
$dumpvars
bx +
x*
x)
x(
x'
b0 &
bx %
bx $
0#
bx !
$end
#50000
1#
#100000
b111111 !
b111111 +
0'
0(
0)
0*
0#
b1 &
b0 %
b0 $
#150000
1#
#200000
b110 !
b110 +
1*
0#
b10 &
b1 %
b1 $
#250000
1#
#300000
b1011011 !
b1011011 +
1)
0*
0#
b11 &
b10 %
b10 $
#350000
1#
#400000
b1001111 !
b1001111 +
1*
0#
b100 &
b11 %
b11 $
#450000
1#
#500000
b1100110 !
b1100110 +
1(
0)
0*
0#
b101 &
b100 %
b100 $
#550000
1#
#600000
b1101101 !
b1101101 +
1*
0#
b110 &
b101 %
b101 $
#650000
1#
#700000
b1111101 !
b1111101 +
1)
0*
0#
b111 &
b110 %
b110 $
#750000
1#
#800000
b111 !
b111 +
1*
0#
b1000 &
b111 %
b111 $
#850000
1#
#900000
b1111111 !
b1111111 +
1'
0(
0)
0*
0#
b1001 &
b1000 %
b1000 $
#950000
1#
#1000000
b1101111 !
b1101111 +
1*
0#
b1010 &
b1001 %
b1001 $
