Complemento1/complemento_a_1.v
module complemento_a_1 (
    //Entradas
    input wire BTN1,
    input wire BTN2,
    input wire BTN3,
    input wire BTN4,

    //Salidas
    output wire LED0,
    output wire LED1,
    output wire LED2,
    output wire LED3
);

    assign LED0 =~BTN1;
    assign LED1 =~BTN2;
    assign LED2 =~BTN3;
    assign LED3 =~BTN4;

endmodule

Complemento1/complemento_a_1_tb.v
`default_nettype none
`define DUMPSTR(x) `"x.vcd`"
`timescale 100ns / 10ns

module complemento_a_1_tb();

parameter DURATION = 10;


reg clk=0;
always #0.5 clk = ~clk;

// Entradas
reg test_BTN1, test_BTN2, test_BTN3, test_BTN4;
//Salidas
wire test_LED0, test_LED1, test_LED2, test_LED3;

complemento_a_1 UUT (
    .BTN1(test_BTN1),
    .BTN2(test_BTN2),
    .BTN3(test_BTN3),
    .BTN4(test_BTN4),
    .LED0(test_LED0),
    .LED1(test_LED1),
    .LED2(test_LED2),
    .LED3(test_LED3)
);

integer  i;
reg [3:0] entradas;

initial begin
    // Inicializa las señales
    $dumpfile(`DUMPSTR(`VCD_OUTPUT));
    $dumpvars(0, complemento_a_1_tb);

    for (i=0; i<16; i=i+1)
    begin
        $display ("Current loop # %0d",i);
        
        #1
        entradas = i;
        test_BTN1 = entradas[0];
        test_BTN2 = entradas[1];
        test_BTN3 = entradas[2];
        test_BTN4 = entradas[3];
    end

    // Finaliza la simulación
    // $display("Simulación completada.");
    #(DURATION) $display("End of simulation");
    $finish;
end

endmodule

Complemento1/complemento_a_1_tb.vcd
$date
	Fri Apr 04 14:06:28 2025
$end
$version
	Icarus Verilog
$end
$timescale
	1ps
$end
$scope module complemento_a_1_tb $end
$var wire 1 ! test_LED3 $end
$var wire 1 " test_LED2 $end
$var wire 1 # test_LED1 $end
$var wire 1 $ test_LED0 $end
$var parameter 32 % DURATION $end
$var reg 1 & clk $end
$var reg 4 ' entradas [3:0] $end
$var reg 1 ( test_BTN1 $end
$var reg 1 ) test_BTN2 $end
$var reg 1 * test_BTN3 $end
$var reg 1 + test_BTN4 $end
$var integer 32 , i [31:0] $end
$scope module UUT $end
$var wire 1 ( BTN1 $end
$var wire 1 ) BTN2 $end
$var wire 1 * BTN3 $end
$var wire 1 + BTN4 $end
$var wire 1 $ LED0 $end
$var wire 1 # LED1 $end
$var wire 1 " LED2 $end
$var wire 1 ! LED3 $end
$upscope $end
$upscope $end
$enddefinitions $end
$comment Show the parameter values. $end
$dumpall
b1010 %
$end
#0
$dumpvars
b0 ,
x+
x*
x)
x(
bx '
0&
x$
x#
x"
x!
$end
#50000
1&
#100000
1!
1"
1#
1$
0&
b1 ,
0+
0*
0)
0(
b0 '
#150000
1&
#200000
0$
0&
b10 ,
1(
b1 '
#250000
1&
#300000
0#
1$
0&
b11 ,
1)
0(
b10 '
#350000
1&
#400000
0$
0&
b100 ,
1(
b11 '
#450000
1&
#500000
0"
1#
1$
0&
b101 ,
1*
0)
0(
b100 '
#550000
1&
#600000
0$
0&
b110 ,
1(
b101 '
#650000
1&
#700000
0#
1$
0&
b111 ,
1)
0(
b110 '
#750000
1&
#800000
0$
0&
b1000 ,
1(
b111 '
#850000
1&
#900000
0!
1"
1#
1$
0&
b1001 ,
1+
0*
0)
0(
b1000 '
#950000
1&
#1000000
0$
0&
b1010 ,
1(
b1001 '
#1050000
1&
#1100000
0#
1$
0&
b1011 ,
1)
0(
b1010 '
#1150000
1&
#1200000
0$
0&
b1100 ,
1(
b1011 '
#1250000
1&
#1300000
0"
1#
1$
0&
b1101 ,
1*
0)
0(
b1100 '
#1350000
1&
#1400000
0$
0&
b1110 ,
1(
b1101 '
#1450000
1&
#1500000
0#
1$
0&
b1111 ,
1)
0(
b1110 '
#1550000
1&
#1600000
0$
0&
b10000 ,
1(
b1111 '
