Hello_world/main.v
module main (
    input wire CLK,       // Entrada de reloj
    output wire LED0       // Salida para el LED
);

// Contador para generar un retardo
reg [31:0] counter = 0;

reg LED0_REG = 0;

always @(posedge CLK) begin
    counter <= counter + 1;
    LED0_REG <= ~LED0_REG; 
    if (counter == 20) begin  // Ajusta este valor para cambiar la velocidad del parpadeo
                      // Cambia el estado del LED
        counter <= 0;              // Reinicia el contador
    end
end

assign  LED0 = LED0_REG;

endmodule

Hello_world/main_tb.v
`define DUMPSTR(x) `"x.vcd`"
`timescale 1ns / 1ps

module main_tb;

    parameter DURATION = 200;

    // Señales de entrada/salida
    reg CLK = 0;          // Señal de reloj
    wire LED0;        // Señal del LED

    // Instancia del módulo principal
    main uut (
        .CLK(CLK),    // Conecta la señal de reloj
        .LED0(LED0)   // Conecta la señal del LED
    );

    // Generación de la señal de reloj
    always begin
        
        #5 CLK = ~CLK;  // Cambia el reloj cada 5 ns (esto genera un reloj de 100 MHz)
    end

    // Bloque inicial para la simulación
    initial begin
        // Inicializa las señales
        $dumpfile(`DUMPSTR(`VCD_OUTPUT));
        $dumpvars(0, main_tb);
        

        // CLK = 0;

        // Duración de la simulación
        // #200;  // Simula durante 200,000,000 ns (200 ms)
        #(DURATION) $display("End of simulation");

        // Finaliza la simulación
        // $display("Simulación completada.");
        $finish;
    end

endmodule

Hello_world/main_tb.vcd
$date
	Wed Mar 05 14:17:43 2025
$end
$version
	Icarus Verilog
$end
$timescale
	1ps
$end
$scope module main_tb $end
$var wire 1 ! LED0 $end
$var parameter 32 " DURATION $end
$var reg 1 # CLK $end
$scope module uut $end
$var wire 1 # CLK $end
$var wire 1 ! LED0 $end
$var reg 1 $ LED0_REG $end
$var reg 32 % counter [31:0] $end
$upscope $end
$upscope $end
$enddefinitions $end
$comment Show the parameter values. $end
$dumpall
b11001000 "
$end
#0
$dumpvars
b0 %
0$
0#
0!
$end
#5000
1!
1$
b1 %
1#
#10000
0#
#15000
0!
0$
b10 %
1#
#20000
0#
#25000
1!
1$
b11 %
1#
#30000
0#
#35000
0!
0$
b100 %
1#
#40000
0#
#45000
1!
1$
b101 %
1#
#50000
0#
#55000
0!
0$
b110 %
1#
#60000
0#
#65000
1!
1$
b111 %
1#
#70000
0#
#75000
0!
0$
b1000 %
1#
#80000
0#
#85000
1!
1$
b1001 %
1#
#90000
0#
#95000
0!
0$
b1010 %
1#
#100000
0#
#105000
1!
1$
b1011 %
1#
#110000
0#
#115000
0!
0$
b1100 %
1#
#120000
0#
#125000
1!
1$
b1101 %
1#
#130000
0#
#135000
0!
0$
b1110 %
1#
#140000
0#
#145000
1!
1$
b1111 %
1#
#150000
0#
#155000
0!
0$
b10000 %
1#
#160000
0#
#165000
1!
1$
b10001 %
1#
#170000
0#
#175000
0!
0$
b10010 %
1#
#180000
0#
#185000
1!
1$
b10011 %
1#
#190000
0#
#195000
0!
0$
b10100 %
1#
