flipflopJK/ffJK.v
module ffJK(
    input wire j,
    input wire k,
    input wire clk,
    output wire Q,Qn
);

reg salida = 0;

always @(posedge clk) begin
    case ({j,k})
    2'b00: salida<=salida;
    2'b01: salida<=1'b0;
    2'b10: salida<=1'b1;
    2'b11: salida<=~salida;
    endcase
end

assign Q = salida;
assign Qn = ~salida;


endmodule

M_estado/M_Estado.v
`include "FFJK/FFJK.v"

module M_Estado(
    input wire CLK,
    input wire Re,
    output wire [2:0] Estados 
);

wire [2:0] Q;
wire [2:0] J,K;

assign J[0] = 1'b1;
assign K[0] = ~Re&(~Q[2]|~Q[1]);

assign J[1] = Re|~Q[2];
assign K[1] = ~Re&((~Q[2]&~Q[0])|(Q[2]&Q[0]));

assign J[2] = Re|~Q[1]|~Q[0];
assign K[2] = ~Re;

genvar i;
    generate
        for (i = 0; i < 3; i = i + 1) begin : FFJK
             ffJK JK_instancia (
                .clk(CLK),
                .j(J[i]),
                .k(K[i]),
                .Q(Q[i])
             );
        end
    endgenerate

assign Estados = Q;

endmodule

M_estado/M_Estado_tb.v
`default_nettype none
`define DUMPSTR(x) `"x.vcd`"
`timescale 100ns / 10ns

module M_Estado_tb();

parameter DURATION = 10;


reg clk_test=0;
always #5 clk_test = ~clk_test;

// Entradas
reg Re_test;
//Salidas
wire [2:0] Estados_test;

M_Estado UUT (
    .CLK(clk_test),
    .Re(Re_test),
    .Estados(Estados_test)
);


initial begin
    // Inicializa las señales
    $dumpfile(`DUMPSTR(`VCD_OUTPUT));
    $dumpvars(0, M_Estado_tb);

    // Inicialización
    Re_test = 0;

    // Espera unos ciclos con Re=0
    #100;

    // Activa Re para volver al estado 7
    Re_test = 1;
    #20;

    // Vuelve a poner Re en 0 para continuar la secuencia
    Re_test = 0;
    #100;

    // Finalizar simulación
    #20;
    $finish;
    end
endmodule

M_estado/M_Estado_tb.vcd
$date
	Fri Jun 06 11:05:35 2025
$end
$version
	Icarus Verilog
$end
$timescale
	1ps
$end
$scope module M_Estado_tb $end
$var wire 3 ! Estados_test [2:0] $end
$var parameter 32 " DURATION $end
$var reg 1 # Re_test $end
$var reg 1 $ clk_test $end
$scope module UUT $end
$var wire 1 $ CLK $end
$var wire 3 % Estados [2:0] $end
$var wire 1 # Re $end
$var wire 3 & Q [2:0] $end
$var wire 3 ' K [2:0] $end
$var wire 3 ( J [2:0] $end
$scope begin FFJK[0] $end
$var parameter 2 ) i $end
$scope module JK_instancia $end
$var wire 1 * Q $end
$var wire 1 + Qn $end
$var wire 1 $ clk $end
$var wire 1 , j $end
$var wire 1 - k $end
$var reg 1 . salida $end
$upscope $end
$upscope $end
$scope begin FFJK[1] $end
$var parameter 2 / i $end
$scope module JK_instancia $end
$var wire 1 0 Q $end
$var wire 1 1 Qn $end
$var wire 1 $ clk $end
$var wire 1 2 j $end
$var wire 1 3 k $end
$var reg 1 4 salida $end
$upscope $end
$upscope $end
$scope begin FFJK[2] $end
$var parameter 3 5 i $end
$scope module JK_instancia $end
$var wire 1 6 Q $end
$var wire 1 7 Qn $end
$var wire 1 $ clk $end
$var wire 1 8 j $end
$var wire 1 9 k $end
$var reg 1 : salida $end
$upscope $end
$upscope $end
$upscope $end
$upscope $end
$enddefinitions $end
$comment Show the parameter values. $end
$dumpall
b10 5
b1 /
b0 )
b1010 "
$end
#0
$dumpvars
0:
19
18
17
06
04
13
12
11
00
0.
1-
1,
1+
0*
b111 (
b111 '
b0 &
b0 %
0$
0#
b0 !
$end
#500000
0-
08
b110 '
02
b1 (
0+
01
07
1*
1.
10
14
b111 !
b111 %
b111 &
16
1:
1$
#1000000
0$
#1500000
03
1-
18
12
b101 '
b111 (
17
11
06
0:
b1 !
b1 %
b1 &
00
04
1$
#2000000
0$
#2500000
0-
b100 '
02
b101 (
1+
01
07
0*
0.
10
14
b110 !
b110 %
b110 &
16
1:
1$
#3000000
0$
#3500000
1-
b101 '
12
08
b11 (
17
0+
06
0:
b11 !
b11 %
b11 &
1*
1.
1$
#4000000
0$
#4500000
13
b111 '
18
b111 (
1+
b10 !
b10 %
b10 &
0*
0.
1$
#5000000
0$
#5500000
02
18
b101 (
07
11
0+
16
1:
00
04
b101 !
b101 %
b101 &
1*
1.
1$
#6000000
0$
#6500000
13
12
b111 '
b111 (
1+
17
0*
0.
b0 !
b0 %
b0 &
06
0:
1$
#7000000
0$
#7500000
0-
08
02
b110 '
b1 (
07
01
0+
16
1:
10
14
b111 !
b111 %
b111 &
1*
1.
1$
#8000000
0$
#8500000
18
1-
03
12
b101 '
b111 (
11
17
00
04
b1 !
b1 %
b1 &
06
0:
1$
#9000000
0$
#9500000
0-
02
b100 '
b101 (
07
01
1+
16
1:
10
14
b110 !
b110 %
b110 &
0*
0.
1$
#10000000
12
09
b111 (
b0 '
0$
1#
#10500000
0+
b111 !
b111 %
b111 &
1*
1.
1$
#11000000
0$
#11500000
1$
#12000000
13
08
02
19
b1 (
b110 '
0$
0#
#12500000
18
1-
03
12
b101 '
b111 (
11
17
00
04
b1 !
b1 %
b1 &
06
0:
1$
#13000000
0$
#13500000
0-
02
b100 '
b101 (
07
01
1+
16
1:
10
14
b110 !
b110 %
b110 &
0*
0.
1$
#14000000
0$
#14500000
1-
08
b101 '
12
b11 (
0+
17
1*
1.
b11 !
b11 %
b11 &
06
0:
1$
#15000000
0$
#15500000
13
b111 '
18
b111 (
1+
b10 !
b10 %
b10 &
0*
0.
1$
#16000000
0$
#16500000
02
b101 (
0+
11
07
1*
1.
00
04
b101 !
b101 %
b101 &
16
1:
1$
#17000000
0$
#17500000
13
12
b111 '
b111 (
17
1+
06
0:
b0 !
b0 %
b0 &
0*
0.
1$
#18000000
0$
#18500000
0-
08
b110 '
02
b1 (
0+
01
07
1*
1.
10
14
b111 !
b111 %
b111 &
16
1:
1$
#19000000
0$
#19500000
03
1-
18
12
b101 '
b111 (
17
11
06
0:
b1 !
b1 %
b1 &
00
04
1$
#20000000
0$
#20500000
0-
b100 '
02
b101 (
1+
01
07
0*
0.
10
14
b110 !
b110 %
b110 &
16
1:
1$
#21000000
0$
#21500000
1-
b101 '
12
08
b11 (
17
0+
06
0:
b11 !
b11 %
b11 &
1*
1.
1$
#22000000
0$
#22500000
13
b111 '
18
b111 (
1+
b10 !
b10 %
b10 &
0*
0.
1$
#23000000
0$
#23500000
02
18
b101 (
07
11
0+
16
1:
00
04
b101 !
b101 %
b101 &
1*
1.
1$
