ALU/suma/suma.v
module suma(
    input wire A, B, Cin,
    output wire S,Cout
    );

    assign S = (~A&~B&Cin)|(~A&B&~Cin)|(A&B&Cin)|(A&~B&~Cin);
    assign Cout = (A&Cin)|(A&B)|(B&Cin);

endmodule

suma/suma_tb.v
`default_nettype none
`define DUMPSTR(x) `"x.vcd`"
`timescale 100ns / 10ns

module suma_tb();

parameter DURATION = 10;


reg clk=0;
always #0.5 clk = ~clk;

// Entradas
reg A_test, B_test, Cin_test;
//Salidas
wire S_test, Cout_test;

suma UUT (
    .A(A_test),
    .B(B_test),
    .Cin(Cin_test),
    .S(S_test),
    .Cout(Cout_test)
);

integer  i;
 

initial begin
    // Inicializa las señales
    $dumpfile(`DUMPSTR(`VCD_OUTPUT));
    $dumpvars(0, suma_tb);

    for (i=0; i<8; i=i+1)
    begin
        $display ("Current loop # %0d",i);
        
        A_test = i[2]; 
        B_test = i[1];
        Cin_test = i[0];
        #1;
        end
    
        // Finaliza la simulación
        // $display("Simulación completada.");
        #(DURATION) $display("End of simulation");
        $finish;
    end
    
endmodule

suma/suma_tb.vcd
$date
	Mon May 12 16:04:03 2025
$end
$version
	Icarus Verilog
$end
$timescale
	1ps
$end
$scope module suma_tb $end
$var wire 1 ! S_test $end
$var wire 1 " Cout_test $end
$var parameter 32 # DURATION $end
$var reg 1 $ A_test $end
$var reg 1 % B_test $end
$var reg 1 & Cin_test $end
$var reg 1 ' clk $end
$var integer 32 ( i [31:0] $end
$scope module UUT $end
$var wire 1 $ A $end
$var wire 1 % B $end
$var wire 1 & Cin $end
$var wire 1 " Cout $end
$var wire 1 ! S $end
$upscope $end
$upscope $end
$enddefinitions $end
$comment Show the parameter values. $end
$dumpall
b1010 #
$end
#0
$dumpvars
b0 (
0'
0&
0%
0$
0"
0!
$end
#50000
1'
#100000
1!
0'
1&
b1 (
#150000
1'
#200000
0'
0&
1%
b10 (
#250000
1'
#300000
0!
1"
0'
1&
b11 (
#350000
1'
#400000
1!
0"
0'
0&
0%
1$
b100 (
#450000
1'
#500000
0!
1"
0'
1&
b101 (
#550000
1'
#600000
0'
0&
1%
b110 (
#650000
1'
#700000
1!
0'
1&
b111 (
#750000
1'
#800000
0'
b1000 (
