flipflopJK/ffJK.v
module ffJK(
    input wire j,
    input wire k,
    input wire clk,
    output wire Q,Qn
);

reg salida = 0;

always @(posedge clk) begin
    case ({j,k})
    2'b00: salida<=salida;
    2'b01: salida<=1'b0;
    2'b10: salida<=1'b1;
    2'b11: salida<=~salida;
    endcase
end

assign Q = salida;
assign Qn = ~salida;


endmodule

flipflopJK/ffJK_tb.v
`default_nettype none
`define DUMPSTR(x) `"x.vcd`"
`timescale 100ns / 10ns

module ffJK_tb();

parameter DURATION = 10;


reg clk_test=0;
always #0.5 clk_test = ~clk_test;

// Entradas
reg j_test, k_test;
//Salidas
wire Q_test,Qn_test;

ffJK UUT (
    .j(j_test),
    .k(k_test),
    .clk(clk_test),
    .Q(Q_test),
    .Qn(Qn_test)
);


initial begin
    // Inicializa las señales
    $dumpfile(`DUMPSTR(`VCD_OUTPUT));
    $dumpvars(0, ffJK_tb);

    // Entradas JK normales con flancos de reloj
    j_test = 1; k_test = 0;   // Set
    #10 j_test = 0; k_test = 1;   // Reset
    #10 j_test = 1; k_test = 1;   // Toggle
    #10 j_test = 0; k_test = 0;   // Hold

    #20 $finish;

end

endmodule

flipflopJK/ffJK_tb.vcd
$date
	Tue May 13 17:35:33 2025
$end
$version
	Icarus Verilog
$end
$timescale
	1ps
$end
$scope module ffJK_tb $end
$var wire 1 ! Qn_test $end
$var wire 1 " Q_test $end
$var parameter 32 # DURATION $end
$var reg 1 $ clk_test $end
$var reg 1 % j_test $end
$var reg 1 & k_test $end
$scope module UUT $end
$var wire 1 " Q $end
$var wire 1 ! Qn $end
$var wire 1 $ clk $end
$var wire 1 % j $end
$var wire 1 & k $end
$var reg 1 ' salida $end
$upscope $end
$upscope $end
$enddefinitions $end
$comment Show the parameter values. $end
$dumpall
b1010 #
$end
#0
$dumpvars
0'
0&
1%
0$
0"
1!
$end
#50000
0!
1"
1'
1$
#100000
0$
#150000
1$
#200000
0$
#250000
1$
#300000
0$
#350000
1$
#400000
0$
#450000
1$
#500000
0$
#550000
1$
#600000
0$
#650000
1$
#700000
0$
#750000
1$
#800000
0$
#850000
1$
#900000
0$
#950000
1$
#1000000
0$
1&
0%
#1050000
1!
0"
0'
1$
#1100000
0$
#1150000
1$
#1200000
0$
#1250000
1$
#1300000
0$
#1350000
1$
#1400000
0$
#1450000
1$
#1500000
0$
#1550000
1$
#1600000
0$
#1650000
1$
#1700000
0$
#1750000
1$
#1800000
0$
#1850000
1$
#1900000
0$
#1950000
1$
#2000000
0$
1%
#2050000
0!
1"
1'
1$
#2100000
0$
#2150000
1!
0"
0'
1$
#2200000
0$
#2250000
0!
1"
1'
1$
#2300000
0$
#2350000
1!
0"
0'
1$
#2400000
0$
#2450000
0!
1"
1'
1$
#2500000
0$
#2550000
1!
0"
0'
1$
#2600000
0$
#2650000
0!
1"
1'
1$
#2700000
0$
#2750000
1!
0"
0'
1$
#2800000
0$
#2850000
0!
1"
1'
1$
#2900000
0$
#2950000
1!
0"
0'
1$
#3000000
0$
0&
0%
