Resta/resta.v
module resta(
    input wire A, B, Bin,
    output wire R,Bout
    );

    assign R = (~A&~B&Bin)|(~A&B&~Bin)|(A&B&Bin)|(A&~B&~Bin);
    assign Bout = (~A&Bin)|(~A&B)|(B&Bin);

endmodule

Resta/resta_tb.v
`default_nettype none
`define DUMPSTR(x) `"x.vcd`"
`timescale 100ns / 10ns

module resta_tb();

parameter DURATION = 10;


reg clk=0;
always #0.5 clk = ~clk;

// Entradas
reg A_test, B_test, Bin_test;
//Salidas
wire R_test, Bout_test;

resta UUT (
    .A(A_test),
    .B(B_test),
    .Bin(Bin_test),
    .R(R_test),
    .Bout(Bout_test)
);

integer  i;
 

initial begin
    // Inicializa las señales
    $dumpfile(`DUMPSTR(`VCD_OUTPUT));
    $dumpvars(0, resta_tb);

    for (i=0; i<8; i=i+1)
    begin
        $display ("Current loop # %0d",i);
        
        A_test = i[2]; 
        B_test = i[1];
        Bin_test = i[0];
        #1;
        end
    
        // Finaliza la simulación
        // $display("Simulación completada.");
        #(DURATION) $display("End of simulation");
        $finish;
    end
    
endmodule

Resta/resta_tb.vcd
$date
	Mon May 12 16:13:51 2025
$end
$version
	Icarus Verilog
$end
$timescale
	1ps
$end
$scope module resta_tb $end
$var wire 1 ! R_test $end
$var wire 1 " Bout_test $end
$var parameter 32 # DURATION $end
$var reg 1 $ A_test $end
$var reg 1 % B_test $end
$var reg 1 & Bin_test $end
$var reg 1 ' clk $end
$var integer 32 ( i [31:0] $end
$scope module UUT $end
$var wire 1 $ A $end
$var wire 1 % B $end
$var wire 1 & Bin $end
$var wire 1 " Bout $end
$var wire 1 ! R $end
$upscope $end
$upscope $end
$enddefinitions $end
$comment Show the parameter values. $end
$dumpall
b1010 #
$end
#0
$dumpvars
b0 (
0'
0&
0%
0$
0"
0!
$end
#50000
1'
#100000
1!
1"
0'
1&
b1 (
#150000
1'
#200000
0'
0&
1%
b10 (
#250000
1'
#300000
0!
0'
1&
b11 (
#350000
1'
#400000
1!
0"
0'
0&
0%
1$
b100 (
#450000
1'
#500000
0!
0'
1&
b101 (
#550000
1'
#600000
0'
0&
1%
b110 (
#650000
1'
#700000
1!
1"
0'
1&
b111 (
#750000
1'
#800000
0'
b1000 (
