Resta/resta.v
module resta(
    input wire A, B, Bin,
    output wire R,Bout
    );

    assign R = (~A&~B&Bin)|(~A&B&~Bin)|(A&B&Bin)|(A&~B&~Bin);
    assign Bout = (~A&Bin)|(~A&B)|(B&Bin);

endmodule

ALU/suma/suma.v
module suma(
    input wire A, B, Cin,
    output wire S,Cout
    );

    assign S = (~A&~B&Cin)|(~A&B&~Cin)|(A&B&Cin)|(A&~B&~Cin);
    assign Cout = (A&Cin)|(A&B)|(B&Cin);

endmodule

ALU/top_alu.v
`include "suma/suma.v"
`include "resta/resta.v"

module top_alu(
    input wire In1,       // Entrada 1 (minuendo/sumando)
    input wire In2,       // Entrada 2 (sustraendo/sumando)
    input wire CB_in,     // Carry/Borrow de entrada
    input wire [2:0] code_op, // Código de operación
    output wire Result,   // Resultado
    output wire CB_out     // Carry/Borrow de salida
);

// Conexiones internas
wire suma_s, suma_c;
wire resta_d, resta_b;

// Instanciar sumador
suma sumador (
    .A(In1),
    .B(In2),
    .Cin(CB_in),
    .S(suma_s),
    .Cout(suma_c)
);

// Instanciar restador
resta restador (
    .A(In1),
    .B(In2),
    .Bin(CB_in),
    .R(resta_d),
    .Bout(resta_b)
);

// Lógica de selección de operación
reg tmp_result, tmp_cb;

always @(*) begin
    case(code_op)
        3'b001: begin // Suma
            tmp_result = suma_s;
            tmp_cb = suma_c;
        end
        3'b010: begin // Resta
            tmp_result = resta_d;
            tmp_cb = resta_b;
        end
        default: begin // Otras operaciones (AND, OR, etc.)
            tmp_result = 1'b0;
            tmp_cb = 1'b0;
        end
    endcase
end

assign Result = tmp_result;
assign CB_out = tmp_cb;

endmodule

ALU/top_alu_tb.v
`default_nettype none
`define DUMPSTR(x) `"x.vcd`"
`timescale 100ns / 10ns

module top_alu_tb();

parameter DURATION = 10;


reg clk=0;
always #0.5 clk = ~clk;

// Entradas
reg In1_test, In2_test, CBin_test;
reg [2:0] code_op_tes;
//Salidas
wire Result_test, CBout_test;

top_alu UUT (
    .In1(In1_test),
    .In2(In2_test),
    .CB_in(CBin_test),
    .code_op(code_op_tes),
    .Result(Result_test),
    .CB_out(CBout_test)
);

integer  i;
 

initial begin
    // Inicializa las señales
    $dumpfile(`DUMPSTR(`VCD_OUTPUT));
    $dumpvars(0, top_alu_tb);

    for (i=0; i<128; i=i+1)
    begin
        $display ("Current loop # %0d",i);
        
        In1_test = i[2]; 
        In2_test = i[1];
        CBin_test = i[0];
        code_op_tes = i[5:3];
        #1;
        end
    
        // Finaliza la simulación
        // $display("Simulación completada.");
        #(DURATION) $display("End of simulation");
        $finish;
    end
    
endmodule

ALU/top_alu_tb.vcd
$date
	Mon May 12 21:33:52 2025
$end
$version
	Icarus Verilog
$end
$timescale
	1ps
$end
$scope module top_alu_tb $end
$var wire 1 ! Result_test $end
$var wire 1 " CBout_test $end
$var parameter 32 # DURATION $end
$var reg 1 $ CBin_test $end
$var reg 1 % In1_test $end
$var reg 1 & In2_test $end
$var reg 1 ' clk $end
$var reg 3 ( code_op_tes [2:0] $end
$var integer 32 ) i [31:0] $end
$scope module UUT $end
$var wire 1 $ CB_in $end
$var wire 1 " CB_out $end
$var wire 1 % In1 $end
$var wire 1 & In2 $end
$var wire 1 ! Result $end
$var wire 3 * code_op [2:0] $end
$var wire 1 + suma_s $end
$var wire 1 , suma_c $end
$var wire 1 - resta_d $end
$var wire 1 . resta_b $end
$var reg 1 / tmp_cb $end
$var reg 1 0 tmp_result $end
$scope module restador $end
$var wire 1 % A $end
$var wire 1 & B $end
$var wire 1 $ Bin $end
$var wire 1 . Bout $end
$var wire 1 - R $end
$upscope $end
$scope module sumador $end
$var wire 1 % A $end
$var wire 1 & B $end
$var wire 1 $ Cin $end
$var wire 1 , Cout $end
$var wire 1 + S $end
$upscope $end
$upscope $end
$upscope $end
$enddefinitions $end
$comment Show the parameter values. $end
$dumpall
b1010 #
$end
#0
$dumpvars
00
0/
0.
0-
0,
0+
b0 *
b0 )
b0 (
0'
0&
0%
0$
0"
0!
$end
#50000
1'
#100000
1-
1+
1.
0'
1$
b1 )
#150000
1'
#200000
0'
0$
1&
b10 )
#250000
1'
#300000
0-
0+
1,
0'
1$
b11 )
#350000
1'
#400000
1-
1+
0.
0,
0'
0$
0&
1%
b100 )
#450000
1'
#500000
0-
0+
1,
0'
1$
b101 )
#550000
1'
#600000
0'
0$
1&
b110 )
#650000
1'
#700000
1-
1+
1.
0'
1$
b111 )
#750000
1'
#800000
0-
0+
0.
0,
0"
0/
0!
00
0'
b1 (
b1 *
0$
0&
0%
b1000 )
#850000
1'
#900000
1-
1!
10
1+
1.
0'
1$
b1001 )
#950000
1'
#1000000
0'
0$
1&
b1010 )
#1050000
1'
#1100000
0!
00
0-
0+
1"
1/
1,
0'
1$
b1011 )
#1150000
1'
#1200000
1!
10
1-
1+
0.
0"
0/
0,
0'
0$
0&
1%
b1100 )
#1250000
1'
#1300000
1"
1/
0!
00
0-
0+
1,
0'
1$
b1101 )
#1350000
1'
#1400000
0'
0$
1&
b1110 )
#1450000
1'
#1500000
1-
1!
10
1+
1.
0'
1$
b1111 )
#1550000
1'
#1600000
0!
00
0-
0+
0"
0/
0.
0,
0'
b10 (
b10 *
0$
0&
0%
b10000 )
#1650000
1'
#1700000
1!
10
1-
1"
1/
1+
1.
0'
1$
b10001 )
#1750000
1'
#1800000
0'
0$
1&
b10010 )
#1850000
1'
#1900000
0!
00
0-
0+
1,
0'
1$
b10011 )
#1950000
1'
#2000000
0"
0/
1!
10
1-
1+
0.
0,
0'
0$
0&
1%
b10100 )
#2050000
1'
#2100000
0!
00
0-
0+
1,
0'
1$
b10101 )
#2150000
1'
#2200000
0'
0$
1&
b10110 )
#2250000
1'
#2300000
1!
10
1-
1"
1/
1+
1.
0'
1$
b10111 )
#2350000
1'
#2400000
0-
0+
0.
0,
0"
0/
0!
00
0'
b11 (
b11 *
0$
0&
0%
b11000 )
#2450000
1'
#2500000
1-
1+
1.
0'
1$
b11001 )
#2550000
1'
#2600000
0'
0$
1&
b11010 )
#2650000
1'
#2700000
0-
0+
1,
0'
1$
b11011 )
#2750000
1'
#2800000
1-
1+
0.
0,
0'
0$
0&
1%
b11100 )
#2850000
1'
#2900000
0-
0+
1,
0'
1$
b11101 )
#2950000
1'
#3000000
0'
0$
1&
b11110 )
#3050000
1'
#3100000
1-
1+
1.
0'
1$
b11111 )
#3150000
1'
#3200000
0-
0+
0.
0,
0'
b100 (
b100 *
0$
0&
0%
b100000 )
#3250000
1'
#3300000
1-
1+
1.
0'
1$
b100001 )
#3350000
1'
#3400000
0'
0$
1&
b100010 )
#3450000
1'
#3500000
0-
0+
1,
0'
1$
b100011 )
#3550000
1'
#3600000
1-
1+
0.
0,
0'
0$
0&
1%
b100100 )
#3650000
1'
#3700000
0-
0+
1,
0'
1$
b100101 )
#3750000
1'
#3800000
0'
0$
1&
b100110 )
#3850000
1'
#3900000
1-
1+
1.
0'
1$
b100111 )
#3950000
1'
#4000000
0-
0+
0.
0,
0'
b101 (
b101 *
0$
0&
0%
b101000 )
#4050000
1'
#4100000
1-
1+
1.
0'
1$
b101001 )
#4150000
1'
#4200000
0'
0$
1&
b101010 )
#4250000
1'
#4300000
0-
0+
1,
0'
1$
b101011 )
#4350000
1'
#4400000
1-
1+
0.
0,
0'
0$
0&
1%
b101100 )
#4450000
1'
#4500000
0-
0+
1,
0'
1$
b101101 )
#4550000
1'
#4600000
0'
0$
1&
b101110 )
#4650000
1'
#4700000
1-
1+
1.
0'
1$
b101111 )
#4750000
1'
#4800000
0-
0+
0.
0,
0'
b110 (
b110 *
0$
0&
0%
b110000 )
#4850000
1'
#4900000
1-
1+
1.
0'
1$
b110001 )
#4950000
1'
#5000000
0'
0$
1&
b110010 )
#5050000
1'
#5100000
0-
0+
1,
0'
1$
b110011 )
#5150000
1'
#5200000
1-
1+
0.
0,
0'
0$
0&
1%
b110100 )
#5250000
1'
#5300000
0-
0+
1,
0'
1$
b110101 )
#5350000
1'
#5400000
0'
0$
1&
b110110 )
#5450000
1'
#5500000
1-
1+
1.
0'
1$
b110111 )
#5550000
1'
#5600000
0-
0+
0.
0,
0'
b111 (
b111 *
0$
0&
0%
b111000 )
#5650000
1'
#5700000
1-
1+
1.
0'
1$
b111001 )
#5750000
1'
#5800000
0'
0$
1&
b111010 )
#5850000
1'
#5900000
0-
0+
1,
0'
1$
b111011 )
#5950000
1'
#6000000
1-
1+
0.
0,
0'
0$
0&
1%
b111100 )
#6050000
1'
#6100000
0-
0+
1,
0'
1$
b111101 )
#6150000
1'
#6200000
0'
0$
1&
b111110 )
#6250000
1'
#6300000
1-
1+
1.
0'
1$
b111111 )
#6350000
1'
#6400000
0-
0+
0.
0,
0'
b0 (
b0 *
0$
0&
0%
b1000000 )
#6450000
1'
#6500000
1-
1+
1.
0'
1$
b1000001 )
#6550000
1'
#6600000
0'
0$
1&
b1000010 )
#6650000
1'
#6700000
0-
0+
1,
0'
1$
b1000011 )
#6750000
1'
#6800000
1-
1+
0.
0,
0'
0$
0&
1%
b1000100 )
#6850000
1'
#6900000
0-
0+
1,
0'
1$
b1000101 )
#6950000
1'
#7000000
0'
0$
1&
b1000110 )
#7050000
1'
#7100000
1-
1+
1.
0'
1$
b1000111 )
#7150000
1'
#7200000
0-
0+
0.
0,
0"
0/
0!
00
0'
b1 (
b1 *
0$
0&
0%
b1001000 )
#7250000
1'
#7300000
1-
1!
10
1+
1.
0'
1$
b1001001 )
#7350000
1'
#7400000
0'
0$
1&
b1001010 )
#7450000
1'
#7500000
0!
00
0-
0+
1"
1/
1,
0'
1$
b1001011 )
#7550000
1'
#7600000
1!
10
1-
1+
0.
0"
0/
0,
0'
0$
0&
1%
b1001100 )
#7650000
1'
#7700000
1"
1/
0!
00
0-
0+
1,
0'
1$
b1001101 )
#7750000
1'
#7800000
0'
0$
1&
b1001110 )
#7850000
1'
#7900000
1-
1!
10
1+
1.
0'
1$
b1001111 )
#7950000
1'
#8000000
0!
00
0-
0+
0"
0/
0.
0,
0'
b10 (
b10 *
0$
0&
0%
b1010000 )
#8050000
1'
#8100000
1!
10
1-
1"
1/
1+
1.
0'
1$
b1010001 )
#8150000
1'
#8200000
0'
0$
1&
b1010010 )
#8250000
1'
#8300000
0!
00
0-
0+
1,
0'
1$
b1010011 )
#8350000
1'
#8400000
0"
0/
1!
10
1-
1+
0.
0,
0'
0$
0&
1%
b1010100 )
#8450000
1'
#8500000
0!
00
0-
0+
1,
0'
1$
b1010101 )
#8550000
1'
#8600000
0'
0$
1&
b1010110 )
#8650000
1'
#8700000
1!
10
1-
1"
1/
1+
1.
0'
1$
b1010111 )
#8750000
1'
#8800000
0-
0+
0.
0,
0"
0/
0!
00
0'
b11 (
b11 *
0$
0&
0%
b1011000 )
#8850000
1'
#8900000
1-
1+
1.
0'
1$
b1011001 )
#8950000
1'
#9000000
0'
0$
1&
b1011010 )
#9050000
1'
#9100000
0-
0+
1,
0'
1$
b1011011 )
#9150000
1'
#9200000
1-
1+
0.
0,
0'
0$
0&
1%
b1011100 )
#9250000
1'
#9300000
0-
0+
1,
0'
1$
b1011101 )
#9350000
1'
#9400000
0'
0$
1&
b1011110 )
#9450000
1'
#9500000
1-
1+
1.
0'
1$
b1011111 )
#9550000
1'
#9600000
0-
0+
0.
0,
0'
b100 (
b100 *
0$
0&
0%
b1100000 )
#9650000
1'
#9700000
1-
1+
1.
0'
1$
b1100001 )
#9750000
1'
#9800000
0'
0$
1&
b1100010 )
#9850000
1'
#9900000
0-
0+
1,
0'
1$
b1100011 )
#9950000
1'
#10000000
1-
1+
0.
0,
0'
0$
0&
1%
b1100100 )
#10050000
1'
#10100000
0-
0+
1,
0'
1$
b1100101 )
#10150000
1'
#10200000
0'
0$
1&
b1100110 )
#10250000
1'
#10300000
1-
1+
1.
0'
1$
b1100111 )
#10350000
1'
#10400000
0-
0+
0.
0,
0'
b101 (
b101 *
0$
0&
0%
b1101000 )
#10450000
1'
#10500000
1-
1+
1.
0'
1$
b1101001 )
#10550000
1'
#10600000
0'
0$
1&
b1101010 )
#10650000
1'
#10700000
0-
0+
1,
0'
1$
b1101011 )
#10750000
1'
#10800000
1-
1+
0.
0,
0'
0$
0&
1%
b1101100 )
#10850000
1'
#10900000
0-
0+
1,
0'
1$
b1101101 )
#10950000
1'
#11000000
0'
0$
1&
b1101110 )
#11050000
1'
#11100000
1-
1+
1.
0'
1$
b1101111 )
#11150000
1'
#11200000
0-
0+
0.
0,
0'
b110 (
b110 *
0$
0&
0%
b1110000 )
#11250000
1'
#11300000
1-
1+
1.
0'
1$
b1110001 )
#11350000
1'
#11400000
0'
0$
1&
b1110010 )
#11450000
1'
#11500000
0-
0+
1,
0'
1$
b1110011 )
#11550000
1'
#11600000
1-
1+
0.
0,
0'
0$
0&
1%
b1110100 )
#11650000
1'
#11700000
0-
0+
1,
0'
1$
b1110101 )
#11750000
1'
#11800000
0'
0$
1&
b1110110 )
#11850000
1'
#11900000
1-
1+
1.
0'
1$
b1110111 )
#11950000
1'
#12000000
0-
0+
0.
0,
0'
b111 (
b111 *
0$
0&
0%
b1111000 )
#12050000
1'
#12100000
1-
1+
1.
0'
1$
b1111001 )
#12150000
1'
#12200000
0'
0$
1&
b1111010 )
#12250000
1'
#12300000
0-
0+
1,
0'
1$
b1111011 )
#12350000
1'
#12400000
1-
1+
0.
0,
0'
0$
0&
1%
b1111100 )
#12450000
1'
#12500000
0-
0+
1,
0'
1$
b1111101 )
#12550000
1'
#12600000
0'
0$
1&
b1111110 )
#12650000
1'
#12700000
1-
1+
1.
0'
1$
b1111111 )
#12750000
1'
#12800000
0'
b10000000 )
