bin2gray/bin2gray.v
module bin2gray(
    input wire [0:3] binario,
    output wire [0:3] gray
);
assign gray[0] = binario[0];
assign gray[1] = binario[0] ^ binario[1];
assign gray[2] = binario[1] ^ binario[2];
assign gray[3] = binario[2] ^ binario[3];
endmodule

bin2gray/bin2gray_tb.v
`default_nettype none
`define DUMPSTR(x) `"x.vcd`"
`timescale 100ns / 10ns

module bin2gray_tb();

parameter DURATION = 10;


reg clk=0;
always #0.5 clk = ~clk;

// Entradas
reg [0:3]binario_test;
//Salidas
wire [0:3]gray_test;

bin2gray UUT (
    .binario(binario_test),
    .gray(gray_test)
);

integer  i;
reg [0:3]temp;
 

initial begin
    // Inicializa las señales
    $dumpfile(`DUMPSTR(`VCD_OUTPUT));
    $dumpvars(0, bin2gray_tb);

    for (i=0;i<16;i=i+1)
        begin
            temp = i;
            binario_test = temp;
            #1;
        end
    //$display ("Current loop # %0d",i);
    
    #1;

    
    
        // Finaliza la simulación
        // $display("Simulación completada.");
    #(DURATION) $display("End of simulation");
    $finish;
    end
    
endmodule

bin2gray/bin2gray_tb.vcd
$date
	Tue Sep 16 11:30:24 2025
$end
$version
	Icarus Verilog
$end
$timescale
	1ps
$end
$scope module bin2gray_tb $end
$var wire 4 ! gray_test [0:3] $end
$var parameter 32 " DURATION $end
$var reg 4 # binario_test [0:3] $end
$var reg 1 $ clk $end
$var reg 4 % temp [0:3] $end
$var integer 32 & i [31:0] $end
$scope module UUT $end
$var wire 4 ' binario [0:3] $end
$var wire 4 ( gray [0:3] $end
$upscope $end
$upscope $end
$enddefinitions $end
$comment Show the parameter values. $end
$dumpall
b1010 "
$end
#0
$dumpvars
b0 (
b0 '
b0 &
b0 %
0$
b0 #
b0 !
$end
#50000
1$
#100000
b1 !
b1 (
0$
b1 #
b1 '
b1 %
b1 &
#150000
1$
#200000
b11 !
b11 (
0$
b10 #
b10 '
b10 %
b10 &
#250000
1$
#300000
b10 !
b10 (
0$
b11 #
b11 '
b11 %
b11 &
#350000
1$
#400000
b110 !
b110 (
0$
b100 #
b100 '
b100 %
b100 &
#450000
1$
#500000
b111 !
b111 (
0$
b101 #
b101 '
b101 %
b101 &
#550000
1$
#600000
b101 !
b101 (
0$
b110 #
b110 '
b110 %
b110 &
#650000
1$
#700000
b100 !
b100 (
0$
b111 #
b111 '
b111 %
b111 &
#750000
1$
#800000
b1100 !
b1100 (
0$
b1000 #
b1000 '
b1000 %
b1000 &
#850000
1$
#900000
b1101 !
b1101 (
0$
b1001 #
b1001 '
b1001 %
b1001 &
#950000
1$
#1000000
b1111 !
b1111 (
0$
b1010 #
b1010 '
b1010 %
b1010 &
#1050000
1$
#1100000
b1110 !
b1110 (
0$
b1011 #
b1011 '
b1011 %
b1011 &
#1150000
1$
#1200000
b1010 !
b1010 (
0$
b1100 #
b1100 '
b1100 %
b1100 &
#1250000
1$
#1300000
b1011 !
b1011 (
0$
b1101 #
b1101 '
b1101 %
b1101 &
#1350000
1$
#1400000
b1001 !
b1001 (
0$
b1110 #
b1110 '
b1110 %
b1110 &
#1450000
1$
#1500000
b1000 !
b1000 (
0$
b1111 #
b1111 '
b1111 %
b1111 &
#1550000
1$
#1600000
0$
b10000 &
